py2mojo/__init__.py
py2mojo/exceptions.py
py2mojo/helpers.py
py2mojo/main.py
py2mojo/rules.py
py2mojo/converters/__init__.py
py2mojo/converters/assignment.py
py2mojo/converters/classdef.py
py2mojo/converters/functiondef.py
py2mojo-0.0.2.dist-info/LICENSE
py2mojo-0.0.2.dist-info/METADATA
py2mojo-0.0.2.dist-info/WHEEL
py2mojo-0.0.2.dist-info/entry_points.txt
py2mojo-0.0.2.dist-info/top_level.txt
py2mojo-0.0.2.dist-info/RECORD
