Metadata-Version: 2.1
Name: py2mojo
Version: 0.0.2
Summary: Automated Python to Mojo code translation
Author-email: Manuel Saelices <msaelices@gmail.com>
License: MIT License
Project-URL: Homepage, https://github.com/msaelices/py2mojo
Project-URL: Bug Reports, https://github.com/msaelices/py2mojo/issues
Project-URL: Source, https://github.com/msaelices/py2mojo
Keywords: mojo,code,development,converter,translator
Classifier: Development Status :: 3 - Alpha
Classifier: Intended Audience :: Developers
Classifier: Topic :: Software Development :: Build Tools
Classifier: License :: OSI Approved :: MIT License
Classifier: Programming Language :: Python :: 3
Classifier: Programming Language :: Python :: 3.11
Classifier: Programming Language :: Python :: 3 :: Only
Requires-Python: >=3.11
License-File: LICENSE
Requires-Dist: tokenize-rt >=5.2.0
Requires-Dist: rich >=13.5.2
Requires-Dist: astor >=0.8.1
Provides-Extra: dev
Requires-Dist: check-manifest ; extra == 'dev'
Provides-Extra: test
Requires-Dist: coverage ; extra == 'test'
Requires-Dist: pytest ; extra == 'test'
